setup.py
pyk/__init__.py
pyk/toolkit.py
pyk/util.py
pyk.egg-info/PKG-INFO
pyk.egg-info/SOURCES.txt
pyk.egg-info/dependency_links.txt
pyk.egg-info/not-zip-safe
pyk.egg-info/requires.txt
pyk.egg-info/top_level.txt