Metadata-Version: 1.1
Name: pyk
Version: 0.3.1
Summary: A simple, yet useful Kubernetes toolkit in Python
Home-page: https://github.com/kubernauts/pyk
Author: Michael Hausenblas
Author-email: michael.hausenblas@gmail.com
License: Apache
Keywords: Kubernetes,containers,appops
Platform: UNKNOWN
Classifier: Development Status :: 3 - Alpha
Classifier: Environment :: Web Environment
Classifier: Intended Audience :: Developers
Classifier: License :: OSI Approved :: Apache Software License
Classifier: Operating System :: OS Independent
Classifier: Programming Language :: Python
